talklabs_stt/__init__.py
talklabs_stt/audio_processor.py
talklabs_stt/client.py
talklabs_stt/decorators.py
talklabs_stt/http_client.py
talklabs_stt/models.py
talklabs_stt/validators.py
talklabs_stt/websocket_stream.py
talklabs_stt-2.0.2.dist-info/licenses/LICENSE
talklabs_stt-2.0.2.dist-info/METADATA
talklabs_stt-2.0.2.dist-info/WHEEL
talklabs_stt-2.0.2.dist-info/top_level.txt
talklabs_stt-2.0.2.dist-info/RECORD
