Metadata-Version: 2.4
Name: talklabs-stt
Version: 2.0.2
Summary: TalkLabs STT SDK - Speech-to-Text API compatible with Deepgram
Author-email: Francisco Lima <franciscorllima@gmail.com>
Maintainer-email: Francisco Lima <franciscorllima@gmail.com>
License-Expression: MIT
Project-URL: Homepage, https://talklabs.com.br
Project-URL: Repository, https://github.com/talklabs/talklabs-stt
Keywords: speech-to-text,stt,transcription,audio,deepgram,talklabs
Classifier: Development Status :: 5 - Production/Stable
Classifier: Intended Audience :: Developers
Classifier: Programming Language :: Python :: 3
Classifier: Programming Language :: Python :: 3.9
Classifier: Programming Language :: Python :: 3.10
Classifier: Programming Language :: Python :: 3.11
Classifier: Programming Language :: Python :: 3.12
Classifier: Programming Language :: Python :: 3.13
Classifier: Topic :: Software Development :: Libraries :: Python Modules
Classifier: Topic :: Multimedia :: Sound/Audio :: Speech
Requires-Python: >=3.9
License-File: LICENSE
Requires-Dist: requests>=2.28.0
Requires-Dist: websockets>=15.0
Requires-Dist: python-dotenv>=1.0.0
Requires-Dist: soundfile>=0.12.0
Requires-Dist: numpy>=1.24.0
Requires-Dist: scipy>=1.10.0
Provides-Extra: dev
Requires-Dist: pytest>=7.4.0; extra == "dev"
Requires-Dist: pytest-asyncio>=0.21.0; extra == "dev"
Requires-Dist: pytest-mock>=3.11.0; extra == "dev"
Requires-Dist: pytest-cov>=4.1.0; extra == "dev"
Requires-Dist: pytest-timeout>=2.1.0; extra == "dev"
Requires-Dist: black>=23.7.0; extra == "dev"
Requires-Dist: flake8>=6.1.0; extra == "dev"
Requires-Dist: mypy>=1.5.0; extra == "dev"
Requires-Dist: rich>=13.0.0; extra == "dev"
Provides-Extra: livekit
Requires-Dist: livekit-plugins-deepgram>=0.6.6; extra == "livekit"
Dynamic: license-file
